CTPC/__init__.py
CTPC/ctpc.py
CTPC/indexPage.py
CTPC/xiaobai.py
CTPC-0.0.1.dist-info/METADATA
CTPC-0.0.1.dist-info/WHEEL
CTPC-0.0.1.dist-info/top_level.txt
CTPC-0.0.1.dist-info/RECORD
