Metadata-Version: 2.1
Name: CTPC
Version: 0.0.1
Summary: Chinese To Python Code
Home-page: https://gitee.com/big_touch/ctpc
Author: Tser
Author-email: 807447312@qq.com
License: UNKNOWN
Platform: UNKNOWN
Classifier: Programming Language :: Python :: 3
Classifier: License :: OSI Approved :: MIT License
Classifier: Operating System :: OS Independent
Requires-Python: >=3.4
Requires-Dist: selenium
